spaceborne/__init__.py
spaceborne/bnt.py
spaceborne/ccl_interface.py
spaceborne/cl_utils.py
spaceborne/config_checker.py
spaceborne/constants.py
spaceborne/cosmo_lib.py
spaceborne/cov_partial_sky.py
spaceborne/cov_real_space.py
spaceborne/covariance.py
spaceborne/ell_utils.py
spaceborne/io_handler.py
spaceborne/julia_integrator.jl
spaceborne/mask_utils.py
spaceborne/oc_interface.py
spaceborne/plot_lib.py
spaceborne/responses.py
spaceborne/sb_lib.py
spaceborne/sigma2_ssc.py
spaceborne/wf_cl_lib.py
spaceborne-2025.7.1.dist-info/LICENSE
spaceborne-2025.7.1.dist-info/METADATA
spaceborne-2025.7.1.dist-info/WHEEL
spaceborne-2025.7.1.dist-info/RECORD
