Metadata-Version: 2.3
Name: Spaceborne
Version: 2025.7.1
Summary: Code to compute the covariance matrix for the 3x2pt photometric survey in harmonic and real space.
License: MIT
Author: davidesciotti
Author-email: 84071067+davidesciotti@users.noreply.github.com
Requires-Python: >=3.12
Classifier: License :: OSI Approved :: MIT License
Classifier: Programming Language :: Python :: 3
Classifier: Programming Language :: Python :: 3.12
Classifier: Programming Language :: Python :: 3.13
Provides-Extra: parallel
Requires-Dist: healpy
Requires-Dist: joblib
Requires-Dist: matplotlib
Requires-Dist: numpy
Requires-Dist: pathos ; extra == "parallel"
Requires-Dist: pyfiglet
Requires-Dist: pylevin
Requires-Dist: pyyaml
Requires-Dist: scipy
Requires-Dist: tqdm
